Workbook

Sheet Data
A1: Location | B1: Category | C1: Period | D1: Type | E1: Budget | F1: Actual
A2: Navy Yard | B2: Sushi | C2: 2026-06 | D2: Revenue | E2: 80000 | F2: 65800
A3: Capitol Hill | B3: Dining | C3: 2026-06 | D3: Revenue | E3: 100000 | F3: 112000
A4: Old Town | B4: Catering | C4: 2026-06 | D4: Revenue | E4: 30000 | F4: 25000
A5: Bethesda | B5: Dining | C5: 2026-06 | D5: Revenue | E5: 90000 | F5: 94000
A6: Navy Yard | B6: Beverage | C6: 2026-06 | D6: Revenue | E6: 40000 | F6: 35000
A7: Capitol Hill | B7: Catering | C7: 2026-06 | D7: Revenue | E7: 20000 | F7: 22000
A8: Old Town | B8: Beverage | C8: 2026-06 | D8: Revenue | E8: 15000 | F8: 17500
A9: Bethesda | B9: Catering | C9: 2026-06 | D9: Revenue | E9: 25000 | F9: 25000
A10: Navy Yard | B10: Labor | C10: 2026-06 | D10: Expense | E10: 40000 | F10: 46500
A11: Capitol Hill | B11: Food | C11: 2026-06 | D11: Expense | E11: 35000 | F11: 31000
A12: Old Town | B12: Labor | C12: 2026-06 | D12: Expense | E12: 20000 | F12: 22000
A13: Bethesda | B13: Food | C13: 2026-06 | D13: Expense | E13: 28000 | F13: 33000
A16: Harbor Table Restaurants | June 2026 | USD
A17: Fictional teaching data. Selected categories only; this is not a complete P&L.
A19: Start with the two prompts in practice-prompts.txt. Keep this Data table unchanged.
A21: Source: stringfestdata/excel-skills-json-demo; original 12-row exercise retained.

Sheet Calculations
A1: Variance calculations | N1: Policy controls
A2: All 12 source rows; partial operating review, not a complete P&L. | N2: Input | O2: Value
N3: Dollar threshold | O3: 5000
A4: Location | B4: Category | C4: Period | D4: Type | E4: Budget | F4: Actual | G4: Variance | H4: VariancePercent | I4: ProfitImpact | J4: Direction | K4: Material | L4: VariancePercentStatus | N4: Percent threshold | O4: 0.1
A5: =INDEX(tblLocationPnL[Location],1) -> Navy Yard | B5: =INDEX(tblLocationPnL[Category],1) -> Sushi | C5: =INDEX(tblLocationPnL[Period],1) -> 2026-06 | D5: =INDEX(tblLocationPnL[Type],1) -> Revenue | E5: =INDEX(tblLocationPnL[Budget],1) -> 80000 | F5: =INDEX(tblLocationPnL[Actual],1) -> 65800 | G5: =F5-E5 -> -14200 | H5: =IF(E5=0,"",G5/E5) -> -0.1775 | I5: =IF(D5="Revenue",G5,-G5) -> -14200 | J5: =IF(I5>0,"Favorable",IF(I5<0,"Unfavorable","On plan")) -> Unfavorable | K5: =OR(ABS(G5)>$O$3,AND(E5>0,ABS(G5)>$O$4*E5)) -> TRUE | L5: =IF(E5=0,"undefined","defined") -> defined
A6: =INDEX(tblLocationPnL[Location],2) -> Capitol Hill | B6: =INDEX(tblLocationPnL[Category],2) -> Dining | C6: =INDEX(tblLocationPnL[Period],2) -> 2026-06 | D6: =INDEX(tblLocationPnL[Type],2) -> Revenue | E6: =INDEX(tblLocationPnL[Budget],2) -> 100000 | F6: =INDEX(tblLocationPnL[Actual],2) -> 112000 | G6: =F6-E6 -> 12000 | H6: =IF(E6=0,"",G6/E6) -> 0.12 | I6: =IF(D6="Revenue",G6,-G6) -> 12000 | J6: =IF(I6>0,"Favorable",IF(I6<0,"Unfavorable","On plan")) -> Favorable | K6: =OR(ABS(G6)>$O$3,AND(E6>0,ABS(G6)>$O$4*E6)) -> TRUE | L6: =IF(E6=0,"undefined","defined") -> defined | N6: Control | O6: Calculated | P6: Policy | Q6: Difference
A7: =INDEX(tblLocationPnL[Location],3) -> Old Town | B7: =INDEX(tblLocationPnL[Category],3) -> Catering | C7: =INDEX(tblLocationPnL[Period],3) -> 2026-06 | D7: =INDEX(tblLocationPnL[Type],3) -> Revenue | E7: =INDEX(tblLocationPnL[Budget],3) -> 30000 | F7: =INDEX(tblLocationPnL[Actual],3) -> 25000 | G7: =F7-E7 -> -5000 | H7: =IF(E7=0,"",G7/E7) -> -0.16666667 | I7: =IF(D7="Revenue",G7,-G7) -> -5000 | J7: =IF(I7>0,"Favorable",IF(I7<0,"Unfavorable","On plan")) -> Unfavorable | K7: =OR(ABS(G7)>$O$3,AND(E7>0,ABS(G7)>$O$4*E7)) -> TRUE | L7: =IF(E7=0,"undefined","defined") -> defined | N7: Revenue Budget | O7: =SUMIFS($E$5:$E$16,$D$5:$D$16,"Revenue") -> 400000 | P7: 400000 | Q7: =O7-P7 -> 0
A8: =INDEX(tblLocationPnL[Location],4) -> Bethesda | B8: =INDEX(tblLocationPnL[Category],4) -> Dining | C8: =INDEX(tblLocationPnL[Period],4) -> 2026-06 | D8: =INDEX(tblLocationPnL[Type],4) -> Revenue | E8: =INDEX(tblLocationPnL[Budget],4) -> 90000 | F8: =INDEX(tblLocationPnL[Actual],4) -> 94000 | G8: =F8-E8 -> 4000 | H8: =IF(E8=0,"",G8/E8) -> 0.044444444 | I8: =IF(D8="Revenue",G8,-G8) -> 4000 | J8: =IF(I8>0,"Favorable",IF(I8<0,"Unfavorable","On plan")) -> Favorable | K8: =OR(ABS(G8)>$O$3,AND(E8>0,ABS(G8)>$O$4*E8)) -> FALSE | L8: =IF(E8=0,"undefined","defined") -> defined | N8: Revenue Actual | O8: =SUMIFS($F$5:$F$16,$D$5:$D$16,"Revenue") -> 396300 | P8: 396300 | Q8: =O8-P8 -> 0
A9: =INDEX(tblLocationPnL[Location],5) -> Navy Yard | B9: =INDEX(tblLocationPnL[Category],5) -> Beverage | C9: =INDEX(tblLocationPnL[Period],5) -> 2026-06 | D9: =INDEX(tblLocationPnL[Type],5) -> Revenue | E9: =INDEX(tblLocationPnL[Budget],5) -> 40000 | F9: =INDEX(tblLocationPnL[Actual],5) -> 35000 | G9: =F9-E9 -> -5000 | H9: =IF(E9=0,"",G9/E9) -> -0.125 | I9: =IF(D9="Revenue",G9,-G9) -> -5000 | J9: =IF(I9>0,"Favorable",IF(I9<0,"Unfavorable","On plan")) -> Unfavorable | K9: =OR(ABS(G9)>$O$3,AND(E9>0,ABS(G9)>$O$4*E9)) -> TRUE | L9: =IF(E9=0,"undefined","defined") -> defined | N9: Expense Budget | O9: =SUMIFS($E$5:$E$16,$D$5:$D$16,"Expense") -> 123000 | P9: 123000 | Q9: =O9-P9 -> 0
A10: =INDEX(tblLocationPnL[Location],6) -> Capitol Hill | B10: =INDEX(tblLocationPnL[Category],6) -> Catering | C10: =INDEX(tblLocationPnL[Period],6) -> 2026-06 | D10: =INDEX(tblLocationPnL[Type],6) -> Revenue | E10: =INDEX(tblLocationPnL[Budget],6) -> 20000 | F10: =INDEX(tblLocationPnL[Actual],6) -> 22000 | G10: =F10-E10 -> 2000 | H10: =IF(E10=0,"",G10/E10) -> 0.1 | I10: =IF(D10="Revenue",G10,-G10) -> 2000 | J10: =IF(I10>0,"Favorable",IF(I10<0,"Unfavorable","On plan")) -> Favorable | K10: =OR(ABS(G10)>$O$3,AND(E10>0,ABS(G10)>$O$4*E10)) -> FALSE | L10: =IF(E10=0,"undefined","defined") -> defined | N10: Expense Actual | O10: =SUMIFS($F$5:$F$16,$D$5:$D$16,"Expense") -> 132500 | P10: 132500 | Q10: =O10-P10 -> 0
A11: =INDEX(tblLocationPnL[Location],7) -> Old Town | B11: =INDEX(tblLocationPnL[Category],7) -> Beverage | C11: =INDEX(tblLocationPnL[Period],7) -> 2026-06 | D11: =INDEX(tblLocationPnL[Type],7) -> Revenue | E11: =INDEX(tblLocationPnL[Budget],7) -> 15000 | F11: =INDEX(tblLocationPnL[Actual],7) -> 17500 | G11: =F11-E11 -> 2500 | H11: =IF(E11=0,"",G11/E11) -> 0.16666667 | I11: =IF(D11="Revenue",G11,-G11) -> 2500 | J11: =IF(I11>0,"Favorable",IF(I11<0,"Unfavorable","On plan")) -> Favorable | K11: =OR(ABS(G11)>$O$3,AND(E11>0,ABS(G11)>$O$4*E11)) -> TRUE | L11: =IF(E11=0,"undefined","defined") -> defined | N11: Partial operating result - Budget | O11: =O7-O9 -> 277000
A12: =INDEX(tblLocationPnL[Location],8) -> Bethesda | B12: =INDEX(tblLocationPnL[Category],8) -> Catering | C12: =INDEX(tblLocationPnL[Period],8) -> 2026-06 | D12: =INDEX(tblLocationPnL[Type],8) -> Revenue | E12: =INDEX(tblLocationPnL[Budget],8) -> 25000 | F12: =INDEX(tblLocationPnL[Actual],8) -> 25000 | G12: =F12-E12 -> 0 | H12: =IF(E12=0,"",G12/E12) -> 0 | I12: =IF(D12="Revenue",G12,-G12) -> 0 | J12: =IF(I12>0,"Favorable",IF(I12<0,"Unfavorable","On plan")) -> On plan | K12: =OR(ABS(G12)>$O$3,AND(E12>0,ABS(G12)>$O$4*E12)) -> FALSE | L12: =IF(E12=0,"undefined","defined") -> defined
A13: =INDEX(tblLocationPnL[Location],9) -> Navy Yard | B13: =INDEX(tblLocationPnL[Category],9) -> Labor | C13: =INDEX(tblLocationPnL[Period],9) -> 2026-06 | D13: =INDEX(tblLocationPnL[Type],9) -> Expense | E13: =INDEX(tblLocationPnL[Budget],9) -> 40000 | F13: =INDEX(tblLocationPnL[Actual],9) -> 46500 | G13: =F13-E13 -> 6500 | H13: =IF(E13=0,"",G13/E13) -> 0.1625 | I13: =IF(D13="Revenue",G13,-G13) -> -6500 | J13: =IF(I13>0,"Favorable",IF(I13<0,"Unfavorable","On plan")) -> Unfavorable | K13: =OR(ABS(G13)>$O$3,AND(E13>0,ABS(G13)>$O$4*E13)) -> TRUE | L13: =IF(E13=0,"undefined","defined") -> defined
A14: =INDEX(tblLocationPnL[Location],10) -> Capitol Hill | B14: =INDEX(tblLocationPnL[Category],10) -> Food | C14: =INDEX(tblLocationPnL[Period],10) -> 2026-06 | D14: =INDEX(tblLocationPnL[Type],10) -> Expense | E14: =INDEX(tblLocationPnL[Budget],10) -> 35000 | F14: =INDEX(tblLocationPnL[Actual],10) -> 31000 | G14: =F14-E14 -> -4000 | H14: =IF(E14=0,"",G14/E14) -> -0.11428571 | I14: =IF(D14="Revenue",G14,-G14) -> 4000 | J14: =IF(I14>0,"Favorable",IF(I14<0,"Unfavorable","On plan")) -> Favorable | K14: =OR(ABS(G14)>$O$3,AND(E14>0,ABS(G14)>$O$4*E14)) -> TRUE | L14: =IF(E14=0,"undefined","defined") -> defined
A15: =INDEX(tblLocationPnL[Location],11) -> Old Town | B15: =INDEX(tblLocationPnL[Category],11) -> Labor | C15: =INDEX(tblLocationPnL[Period],11) -> 2026-06 | D15: =INDEX(tblLocationPnL[Type],11) -> Expense | E15: =INDEX(tblLocationPnL[Budget],11) -> 20000 | F15: =INDEX(tblLocationPnL[Actual],11) -> 22000 | G15: =F15-E15 -> 2000 | H15: =IF(E15=0,"",G15/E15) -> 0.1 | I15: =IF(D15="Revenue",G15,-G15) -> -2000 | J15: =IF(I15>0,"Favorable",IF(I15<0,"Unfavorable","On plan")) -> Unfavorable | K15: =OR(ABS(G15)>$O$3,AND(E15>0,ABS(G15)>$O$4*E15)) -> FALSE | L15: =IF(E15=0,"undefined","defined") -> defined
A16: =INDEX(tblLocationPnL[Location],12) -> Bethesda | B16: =INDEX(tblLocationPnL[Category],12) -> Food | C16: =INDEX(tblLocationPnL[Period],12) -> 2026-06 | D16: =INDEX(tblLocationPnL[Type],12) -> Expense | E16: =INDEX(tblLocationPnL[Budget],12) -> 28000 | F16: =INDEX(tblLocationPnL[Actual],12) -> 33000 | G16: =F16-E16 -> 5000 | H16: =IF(E16=0,"",G16/E16) -> 0.17857143 | I16: =IF(D16="Revenue",G16,-G16) -> -5000 | J16: =IF(I16>0,"Favorable",IF(I16<0,"Unfavorable","On plan")) -> Unfavorable | K16: =OR(ABS(G16)>$O$3,AND(E16>0,ABS(G16)>$O$4*E16)) -> TRUE | L16: =IF(E16=0,"undefined","defined") -> defined

Sheet Review
A1: June 2026 variance review
A2: Snapshot: rerun this review after source or threshold changes to rebuild filtering, sorting, and commentary.
A4: Location | B4: Line item | C4: Budget | D4: Actual | E4: Variance $ | F4: Variance % | G4: Direction | H4: Documented driver
A5: =Calculations!A5 -> Navy Yard | B5: =Calculations!B5 -> Sushi | C5: =Calculations!E5 -> 80000 | D5: =Calculations!F5 -> 65800 | E5: =Calculations!G5 -> -14200 | F5: =Calculations!H5 -> -0.1775 | G5: =Calculations!J5 -> Unfavorable | H5: Reduced sushi service during a kitchen repair lowered sales.
A6: =Calculations!A13 -> Navy Yard | B6: =Calculations!B13 -> Labor | C6: =Calculations!E13 -> 40000 | D6: =Calculations!F13 -> 46500 | E6: =Calculations!G13 -> 6500 | F6: =Calculations!H13 -> 0.1625 | G6: =Calculations!J13 -> Unfavorable | H6: Overtime during the kitchen repair increased labor cost.
A7: =Calculations!A16 -> Bethesda | B7: =Calculations!B16 -> Food | C7: =Calculations!E16 -> 28000 | D7: =Calculations!F16 -> 33000 | E7: =Calculations!G16 -> 5000 | F7: =Calculations!H16 -> 0.17857143 | G7: =Calculations!J16 -> Unfavorable | H7: driver not documented
A8: =Calculations!A9 -> Navy Yard | B8: =Calculations!B9 -> Beverage | C8: =Calculations!E9 -> 40000 | D8: =Calculations!F9 -> 35000 | E8: =Calculations!G9 -> -5000 | F8: =Calculations!H9 -> -0.125 | G8: =Calculations!J9 -> Unfavorable | H8: driver not documented
A9: =Calculations!A7 -> Old Town | B9: =Calculations!B7 -> Catering | C9: =Calculations!E7 -> 30000 | D9: =Calculations!F7 -> 25000 | E9: =Calculations!G7 -> -5000 | F9: =Calculations!H7 -> -0.16666667 | G9: =Calculations!J7 -> Unfavorable | H9: A corporate client canceled its June catering event.
A10: =Calculations!A6 -> Capitol Hill | B10: =Calculations!B6 -> Dining | C10: =Calculations!E6 -> 100000 | D10: =Calculations!F6 -> 112000 | E10: =Calculations!G6 -> 12000 | F10: =Calculations!H6 -> 0.12 | G10: =Calculations!J6 -> Favorable | H10: Additional private dining bookings increased sales.
A11: =Calculations!A14 -> Capitol Hill | B11: =Calculations!B14 -> Food | C11: =Calculations!E14 -> 35000 | D11: =Calculations!F14 -> 31000 | E11: =Calculations!G14 -> -4000 | F11: =Calculations!H14 -> -0.11428571 | G11: =Calculations!J14 -> Favorable | H11: A negotiated supplier discount reduced food cost.
A12: =Calculations!A11 -> Old Town | B12: =Calculations!B11 -> Beverage | C12: =Calculations!E11 -> 15000 | D12: =Calculations!F11 -> 17500 | E12: =Calculations!G11 -> 2500 | F12: =Calculations!H11 -> 0.16666667 | G12: =Calculations!J11 -> Favorable | H12: An expanded patio schedule increased beverage sales.

Sheet Manager
A1: June 2026 manager review
A2: Snapshot: rerun this review after source or threshold changes to rebuild filtering, sorting, and commentary.
A4: Location | B4: Line item | C4: Vs budget | D4: Direction | E4: Documented driver
A5: =Calculations!A5 -> Navy Yard | B5: =Calculations!B5 -> Sushi | C5: =Calculations!G5 -> -14200 | D5: =Calculations!J5 -> Unfavorable | E5: Reduced sushi service during a kitchen repair lowered sales.
A6: =Calculations!A13 -> Navy Yard | B6: =Calculations!B13 -> Labor | C6: =Calculations!G13 -> 6500 | D6: =Calculations!J13 -> Unfavorable | E6: Overtime during the kitchen repair increased labor cost.
A7: =Calculations!A16 -> Bethesda | B7: =Calculations!B16 -> Food | C7: =Calculations!G16 -> 5000 | D7: =Calculations!J16 -> Unfavorable | E7: driver not documented
A8: =Calculations!A9 -> Navy Yard | B8: =Calculations!B9 -> Beverage | C8: =Calculations!G9 -> -5000 | D8: =Calculations!J9 -> Unfavorable | E8: driver not documented
A9: =Calculations!A7 -> Old Town | B9: =Calculations!B7 -> Catering | C9: =Calculations!G7 -> -5000 | D9: =Calculations!J7 -> Unfavorable | E9: A corporate client canceled its June catering event.
A10: =Calculations!A6 -> Capitol Hill | B10: =Calculations!B6 -> Dining | C10: =Calculations!G6 -> 12000 | D10: =Calculations!J6 -> Favorable | E10: Additional private dining bookings increased sales.
A11: =Calculations!A14 -> Capitol Hill | B11: =Calculations!B14 -> Food | C11: =Calculations!G14 -> -4000 | D11: =Calculations!J14 -> Favorable | E11: A negotiated supplier discount reduced food cost.
A12: =Calculations!A11 -> Old Town | B12: =Calculations!B11 -> Beverage | C12: =Calculations!G11 -> 2500 | D12: =Calculations!J11 -> Favorable | E12: An expanded patio schedule increased beverage sales.
